housepaint/__init__.py
housepaint/paint.py
housepaint/pigments.py
housepaint/premixed.py
housepaint-0.0.10.dist-info/LICENSE
housepaint-0.0.10.dist-info/WHEEL
housepaint-0.0.10.dist-info/METADATA
housepaint-0.0.10.dist-info/RECORD
