Metadata-Version: 2.1
Name: housepaint
Version: 0.0.10
Summary: Colour all the output!
Home-page: https://github.com/nicklambourne/housepaint
License: BSD-3-Clause
Author: Nicholas Lambourne
Author-email: nick@ndl.im
Requires-Python: >=3.6,<4.0
Classifier: License :: OSI Approved :: BSD License
Classifier: Operating System :: OS Independent
Classifier: Programming Language :: Python :: 3
Classifier: Programming Language :: Python :: 3.6
Classifier: Programming Language :: Python :: 3.7
Classifier: Programming Language :: Python :: 3.8
Classifier: Programming Language :: Python :: 3.9
Classifier: Topic :: Software Development :: Documentation
Classifier: Topic :: Software Development :: Libraries :: Python Modules
Project-URL: Documentation, https://github.com/nicklambourne/housepaint
Project-URL: Repository, https://github.com/nicklambourne/housepaint
